datatc/__init__.py
datatc/data_directory.py
datatc/data_interface.py
datatc/data_manager.py
datatc/data_processor.py
datatc/git_utilities.py
datatc/self_aware_data.py
datatc/dashboard/__init__.py
datatc/dashboard/dashboard.py
datatc-0.1.1.dist-info/LICENSE
datatc-0.1.1.dist-info/METADATA
datatc-0.1.1.dist-info/WHEEL
datatc-0.1.1.dist-info/entry_points.txt
datatc-0.1.1.dist-info/top_level.txt
datatc-0.1.1.dist-info/RECORD
