Metadata-Version: 2.1
Name: datatc
Version: 0.1.1
Summary: Automate every-day interactions with your data.
Home-page: https://github.com/uzh-dqbm-cmi/data-traffic-control
Author: Laura Kinkead
License: UNKNOWN
Project-URL: Bug Tracker, https://github.com/uzh-dqbm-cmi/data-traffic-control/issues
Project-URL: Documentation, https://data-traffic-control.readthedocs.io/en/latest/
Project-URL: Source Code, https://github.com/uzh-dqbm-cmi/data-traffic-control
Platform: UNKNOWN
Classifier: Programming Language :: Python :: 3
Classifier: License :: OSI Approved :: MIT License
Classifier: Operating System :: OS Independent
Classifier: Development Status :: 2 - Pre-Alpha
Classifier: Intended Audience :: Science/Research
Classifier: Topic :: Scientific/Engineering
Requires-Python: >3.7.0
Requires-Dist: dill
Requires-Dist: flake8
Requires-Dist: gitpython
Requires-Dist: pandas
Requires-Dist: pyyaml
Requires-Dist: xlrd
Provides-Extra: app
Requires-Dist: dash ; extra == 'app'
Requires-Dist: dash-cytoscape ; extra == 'app'
Requires-Dist: dash-html-components ; extra == 'app'
Requires-Dist: dash-core-components ; extra == 'app'
Provides-Extra: docs
Requires-Dist: sphinx-autodoc-typehints ; extra == 'docs'
Provides-Extra: pdf
Requires-Dist: pymupdf ; extra == 'pdf'
